emailid_finder.py
fake_email_identifier-0.0.2.dist-info/LICENSE
fake_email_identifier-0.0.2.dist-info/METADATA
fake_email_identifier-0.0.2.dist-info/WHEEL
fake_email_identifier-0.0.2.dist-info/top_level.txt
fake_email_identifier-0.0.2.dist-info/RECORD
