Metadata-Version: 2.1
Name: fake-email-identifier
Version: 0.1.4
Summary: This will find the email-id is 'True' or 'Flase'
Home-page: https://github.com/teamtact/fake-email-identifier
License: UNKNOWN
Platform: UNKNOWN
Classifier: Programming Language :: Python :: 3
Classifier: License :: OSI Approved :: MIT License
Classifier: Operating System :: OS Independent
